ImageDown/__init__.py
ImageDown-0.7.1.dist-info/LICENSE
ImageDown-0.7.1.dist-info/METADATA
ImageDown-0.7.1.dist-info/WHEEL
ImageDown-0.7.1.dist-info/top_level.txt
ImageDown-0.7.1.dist-info/RECORD
