Metadata-Version: 2.1
Name: ImageDown
Version: 0.7.1
Summary: [WIP] Google Images full-photo downloader
Home-page: https://github.com/quiec/ImageDown
Author: Yusuf Usta
Author-email: yusuf@fusuf.codes
Maintainer: Yusuf Usta
Maintainer-email: yusuf@fusuf.codes
License: GPL3
Keywords: Google,Yandex,Image,Downloader,Google-image
Platform: UNKNOWN
Classifier: Intended Audience :: Developers
Classifier: License :: OSI Approved :: GNU General Public License v3 (GPLv3)
Classifier: Programming Language :: Python :: 3.6
Classifier: Programming Language :: Python :: 3.7
Classifier: Programming Language :: Python :: 3.8
Classifier: Programming Language :: Python :: 3.9
Requires-Dist: selenium
Requires-Dist: chromedriver-autoinstaller
Requires-Dist: requests
